pyxavi/__init__.py
pyxavi/config.py
pyxavi/debugger.py
pyxavi/dictionary.py
pyxavi/janitor.py
pyxavi/logger.py
pyxavi/media.py
pyxavi/network.py
pyxavi/queue_stack.py
pyxavi/stopwatch.py
pyxavi/storage.py
pyxavi/terminal_color.py
pyxavi/text.py
pyxavi/url.py
pyxavi-1.3.1.dist-info/LICENSE
pyxavi-1.3.1.dist-info/METADATA
pyxavi-1.3.1.dist-info/WHEEL
pyxavi-1.3.1.dist-info/RECORD
