Metadata-Version: 2.3
Name: pyxavi
Version: 1.3.1
Summary: Set of utilities to assist on simple Python projects
License: GPLv3
Author: Xavier Arnaus
Author-email: xavi@arnaus.net
Requires-Python: >=3.9,<4.0
Classifier: License :: OSI Approved :: GNU General Public License v3 (GPLv3)
Classifier: License :: Other/Proprietary License
Classifier: Operating System :: OS Independent
Classifier: Programming Language :: Python :: 3
Classifier: Programming Language :: Python :: 3.9
Classifier: Programming Language :: Python :: 3.10
Classifier: Programming Language :: Python :: 3.11
Classifier: Programming Language :: Python :: 3.12
Classifier: Programming Language :: Python :: 3.13
Requires-Dist: beautifulsoup4 (>=4.11,<5.0)
Requires-Dist: emoji (>=2.14.1,<3.0.0)
Requires-Dist: feedparser (>=6.0.10,<7.0.0)
Requires-Dist: multiprocessing-logging (>=0.3.4,<0.4.0)
Requires-Dist: python-slugify (>=7.0.0,<8.0.0)
Requires-Dist: pyyaml (>=6.0.1,<7.0.0)
Requires-Dist: requests (>=2.28.0,<3.0.0)
Requires-Dist: validators (>=0.22.0,<0.23.0)
Project-URL: Homepage, https://github.com/XaviArnaus/pyxavi
Project-URL: Repository, https://github.com/XaviArnaus/pyxavi
